aticli/__init__.py
aticli/__main__.py
aticli/main.py
atlassible/__init__.py
atlassible/atl_utils.py
atlassible/myself.py
atlassible-0.1.1.dist-info/entry_points.txt
atlassible-0.1.1.dist-info/LICENSE
atlassible-0.1.1.dist-info/METADATA
atlassible-0.1.1.dist-info/WHEEL
atlassible-0.1.1.dist-info/RECORD
